bluez_dbus_emulator/__init__.py
bluez_dbus_emulator/adapter1.py
bluez_dbus_emulator/device1.py
bluez_dbus_emulator/emulator.py
bluez_dbus_emulator/gattcharacteristic1.py
bluez_dbus_emulator/gattservice1.py
bluez_dbus_emulator-0.1.0.dist-info/LICENSE
bluez_dbus_emulator-0.1.0.dist-info/METADATA
bluez_dbus_emulator-0.1.0.dist-info/WHEEL
bluez_dbus_emulator-0.1.0.dist-info/top_level.txt
bluez_dbus_emulator-0.1.0.dist-info/zip-safe
bluez_dbus_emulator-0.1.0.dist-info/RECORD
