Metadata-Version: 2.1
Name: bluez-dbus-emulator
Version: 0.1.0
Summary: Python BlueZ DBus emulator
Home-page: https://github.com/OpenBluetoothToolbox/python_bluez_dbus_emulator
Author: Kevin Dewald
License: UNKNOWN
Platform: UNKNOWN
Classifier: Development Status :: 4 - Beta
Classifier: License :: OSI Approved :: MIT License
Classifier: Programming Language :: Python :: 3
Classifier: Programming Language :: Python :: 3.5
Classifier: Programming Language :: Python :: 3.6
Classifier: Programming Language :: Python :: 3.7
Classifier: Programming Language :: Python :: 3.8
Classifier: Programming Language :: Python :: 3.9
Classifier: Programming Language :: Python :: 3 :: Only
Requires-Python: >=3.5.6
Requires-Dist: dbus-next
